{
    "gildong": {
        "36c63692-2d0e-411c-890d-d4275188139a": {
            "balance": 15000,
            "histories": [
                {
                    "dAmount": 10000,
                    "dHistory": "월급",
                    "dRegDate": "2026-06-02 10:24:37",
                    "dModDate": "2026-06-02 10:24:37"
                },
                {
                    "dAmount": 5000,
                    "dHistory": "월급",
                    "dRegDate": "2026-06-02 10:24:28",
                    "dModDate": "2026-06-02 10:24:28"
                }
            ]
        }
    }
}